LICENSE
chromemarks/__init__.py
chromemarks/chrome_system_paths.py
chromemarks/models.py
chromemarks-1.0.1.dist-info/LICENSE
chromemarks-1.0.1.dist-info/WHEEL
chromemarks-1.0.1.dist-info/METADATA
chromemarks-1.0.1.dist-info/RECORD
